{
  "id": "lair-of-tarn-razorlor-miniquest",
  "title": "Lair of Tarn Razorlor (miniquest)",
  "isMiniquest": true,
  "isSeasonal": false,
  "guideLastUpdated": "2026-07-06T22:50:07.376Z",
  "icon": "https://runescape.wiki/images/Lair_of_Tarn_Razorlor_%28miniquest%29_icon.png",
  "entityIcon": null,
  "series": null,
  "seriesNth": null,
  "age": "ambiguous",
  "timeline": "heroic",
  "members": true,
  "voiceOver": false,
  "combatLevel": "70-79",
  "difficulty": "Experienced",
  "length": "Medium",
  "releaseDate": "22 January 2007",
  "area": "Morytania",
  "startPoint": {
    "en": "Recover the diary of Tarn Razorlor. The entrance to Tarn's lair is on the north wall of the ground floor of the Abandoned Mine, accessed via the surface cart tunnel. (via )",
    "es": "Recupera el diario de Tarn Razorlor. La entrada a la guarida de Tarn está en la pared norte de la planta baja de la Abandoned Mine, a la que se accede a través del túnel de la vagoneta de superficie. (vía)"
  },
  "requirements": {
    "quests": [
      {
        "title": "Haunted Mine",
        "children": [
          {
            "title": "Ability to enter Morytania",
            "matchTitle": "Morytania"
          }
        ]
      }
    ],
    "skills": [
      {
        "skill": "Slayer",
        "level": 40
      }
    ]
  },
  "followsEvents": [],
  "items": [],
  "recommended": [
    {
      "name": "Armour and weapons",
      "display": "Armour and weapons",
      "image": null
    },
    {
      "name": "Food and potions",
      "display": "Food and potions",
      "image": null
    },
    {
      "name": "Ring of slaying",
      "display": "Ring of slaying to teleport to the entrance to Tarn's lair",
      "image": "https://runescape.wiki/images/thumb/Ring_of_slaying_detail.png/100px-Ring_of_slaying_detail.png?84846"
    }
  ],
  "kills": [
    "Tarn Razorlor (level 79)"
  ],
  "rewards": [
    {
      "type": "xp",
      "skill": "Slayer",
      "amount": 5000,
      "display": "5,000 experience",
      "image": "https://runescape.wiki/images/Slayer-icon.png?ecab5"
    },
    {
      "type": "item",
      "name": "Tarn's diary",
      "display": "Tarn's diary",
      "image": "https://runescape.wiki/images/thumb/Tarn%27s_diary_detail.png/100px-Tarn%27s_diary_detail.png?ae1e8"
    },
    {
      "type": "item",
      "name": "Salve amulet(e)",
      "display": "Ability to create enchanted salve amulets, by using Tarn's diary on salve amulets.",
      "image": null
    },
    {
      "type": "item",
      "name": "Access to terror dogs in Tarn's lair",
      "display": "Access to terror dogs in Tarn's lair",
      "image": null
    },
    {
      "type": "item",
      "name": "Undead Dungeon",
      "display": "Undead Dungeon",
      "group": "Music unlocked",
      "image": null
    }
  ],
  "rewardBannerImage": "https://runescape.wiki/images/Lair_of_Tarn_Razorlor_%28miniquest%29_reward.png?6bf96",
  "postQuest": [],
  "steps": [
    {
      "index": 0,
      "isImage": true,
      "section": "Getting to Tarn Razorlor",
      "filename": "Tarn's Lair map.png",
      "caption": "A solution to navigating the maze.",
      "image": "https://runescape.wiki/images/Tarn%27s_Lair_map.png?640e5"
    },
    {
      "index": 1,
      "indent": 0,
      "section": "Getting to Tarn Razorlor",
      "text": {
        "en": "Using a Ring of slaying will teleport the player directly to Tarn's lair, skipping most of the quest.",
        "es": "Usar un Ring of slaying teletransportará al jugador directamente a la guarida de Tarn, saltándose la mayor parte de la misión."
      },
      "chatOptions": []
    },
    {
      "index": 2,
      "indent": 1,
      "section": "Getting to Tarn Razorlor",
      "text": {
        "en": "Alternatively, enter level 1 of the abandoned mine by climbing over the mine cart west of the secret entrance and crawling down the cart tunnel.",
        "es": "Alternativamente, entra al nivel 1 de la Abandoned Mine trepando por la vagoneta al oeste de la entrada secreta y arrastrándote por el túnel de la vagoneta."
      },
      "chatOptions": []
    },
    {
      "index": 3,
      "indent": 1,
      "section": "Getting to Tarn Razorlor",
      "text": {
        "en": "Head north and enter the entrance. Watch for skeletons and possessed pickaxes.",
        "es": "Dirígete al norte y entra por la entrada. Ten cuidado con los esqueletos y los picos poseídos."
      },
      "chatOptions": []
    },
    {
      "index": 4,
      "indent": 1,
      "section": "Getting to Tarn Razorlor",
      "text": {
        "en": "Navigate the maze, disarm traps along the way or be hit by damage. Watch for skeletons and zombies throughout the maze.",
        "es": "Recorre el laberinto, desarma las trampas por el camino o recibirás daño. Ten cuidado con los esqueletos y zombis por todo el laberinto."
      },
      "chatOptions": []
    },
    {
      "index": 5,
      "indent": 2,
      "section": "Getting to Tarn Razorlor",
      "text": {
        "en": "For help see Tarn's Lair#Route",
        "es": "Para ayuda, consulta Tarn's Lair#Route"
      },
      "chatOptions": []
    },
    {
      "index": 6,
      "indent": 0,
      "section": "Fighting Tarn Razorlor",
      "text": {
        "en": "Kill both Terror dogs, Mutant tarn and Tarn",
        "es": "Mata a ambos Terror dogs, al Mutant tarn y a Tarn"
      },
      "chatOptions": []
    },
    {
      "index": 7,
      "indent": 0,
      "section": "Fighting Tarn Razorlor",
      "text": {
        "en": "Head north through the passageway and take Tarn's diary.",
        "es": "Dirígete al norte a través del pasadizo y coge el diario de Tarn."
      },
      "chatOptions": []
    }
  ]
}