{
  "id": "once-upon-a-time-in-gielinor",
  "title": "Once Upon a Time in Gielinor",
  "isMiniquest": false,
  "isSeasonal": false,
  "guideLastUpdated": "2026-07-07T14:02:07.513Z",
  "icon": null,
  "entityIcon": "https://runescape.wiki/images/Once_Upon_a_Time_in_Gielinor_entity_icon.png?5315c",
  "series": null,
  "seriesNth": null,
  "age": "6",
  "timeline": "world guardian",
  "members": true,
  "voiceOver": false,
  "combatLevel": "none",
  "difficulty": "Novice",
  "length": null,
  "releaseDate": "22 November 2021",
  "area": "Varrock",
  "startPoint": {
    "en": "",
    "es": "Por favor, proporciona el texto que deseas traducir."
  },
  "requirements": {
    "quests": [],
    "skills": []
  },
  "followsEvents": [],
  "items": [],
  "recommended": [],
  "kills": [],
  "rewards": [],
  "rewardBannerImage": null,
  "postQuest": [],
  "steps": [],
  "guideNote": {
    "en": "This quest is a hub for several sub-quests, each already listed separately in this app with its own step-by-step guide. There isn't a single walkthrough for the hub itself — check the wiki page for the full overview.",
    "es": "Esta misión es un resumen que agrupa varias sub-misiones, cada una ya listada por separado en esta app con su propia guía paso a paso. No existe una guía única para la misión en sí — consulta la página del wiki para ver el resumen completo."
  }
}